aiosvkmimer/__init__.py
aiosvkmimer/client.py
aiosvkmimer-0.1.15.dist-info/LICENSE.txt
aiosvkmimer-0.1.15.dist-info/METADATA
aiosvkmimer-0.1.15.dist-info/WHEEL
aiosvkmimer-0.1.15.dist-info/top_level.txt
aiosvkmimer-0.1.15.dist-info/RECORD
