Metadata-Version: 2.1
Name: aiosvkmimer
Version: 0.1.15
Summary: Asyncio library for SVK Mimer
Author-email: Robin Ostlund <me@robinostlund.name>
Project-URL: Homepage, https://github.com/robinostlund/aiosvkmimer
Project-URL: Bug Tracker, https://github.com/robinostlund/aiosvkmimer/issues
Classifier: Programming Language :: Python :: 3
Classifier: License :: OSI Approved :: GNU General Public License v3 (GPLv3)
Classifier: Operating System :: OS Independent
Requires-Python: >3.7
License-File: LICENSE.txt
Requires-Dist: asyncio
Requires-Dist: aiohttp
Requires-Dist: pandas
Requires-Dist: zstandard
